fastmodels/__init__.py
fastmodels/client.py
fastmodels/response_params.py
fastmodels/tests/__init__.py
fastmodels/tests/agent_completion_test.py
fastmodels/tests/agent_create_and_run_test.py
fastmodels/tests/agent_submit_tool_outputs_stream_test.py
fastmodels/tests/agent_submit_tool_outputs_test.py
fastmodels/tests/chat_completion_test.py
fastmodels/tests/code_review_test.py
fastmodels/tests/doc_parse_test.py
fastmodels/tests/doc_summarizer_test.py
fastmodels/tests/image_summarize_test.py
fastmodels/tests/meeting_minutes_test.py
fastmodels/tests/pota-anlyst_test.py
fastmodels/tests/speech_to_text_test.py
sophnet/__init__.py
sophnet/__main__.py
sophnet/_base_client.py
sophnet/_client.py
sophnet/_compat.py
sophnet/_constants.py
sophnet/_exceptions.py
sophnet/_files.py
sophnet/_legacy_response.py
sophnet/_models.py
sophnet/_module_client.py
sophnet/_qs.py
sophnet/_resource.py
sophnet/_response.py
sophnet/_streaming.py
sophnet/_types.py
sophnet/_version.py
sophnet/client.py
sophnet/pagination.py
sophnet/response_params.py
sophnet/version.py
sophnet/_extras/__init__.py
sophnet/_extras/_common.py
sophnet/_extras/numpy_proxy.py
sophnet/_extras/pandas_proxy.py
sophnet/_utils/__init__.py
sophnet/_utils/_logs.py
sophnet/_utils/_proxy.py
sophnet/_utils/_reflection.py
sophnet/_utils/_streams.py
sophnet/_utils/_sync.py
sophnet/_utils/_transform.py
sophnet/_utils/_typing.py
sophnet/_utils/_utils.py
sophnet/cli/__init__.py
sophnet/cli/_cli.py
sophnet/cli/_errors.py
sophnet/cli/_models.py
sophnet/cli/_progress.py
sophnet/cli/_utils.py
sophnet/cli/_api/__init__.py
sophnet/cli/_api/_main.py
sophnet/cli/_api/audio.py
sophnet/cli/_api/completions.py
sophnet/cli/_api/files.py
sophnet/cli/_api/image.py
sophnet/cli/_api/models.py
sophnet/cli/_api/chat/__init__.py
sophnet/cli/_api/chat/completions.py
sophnet/cli/_tools/__init__.py
sophnet/cli/_tools/_main.py
sophnet/cli/_tools/fine_tunes.py
sophnet/cli/_tools/migrate.py
sophnet/lib/__init__.py
sophnet/lib/_old_api.py
sophnet-0.0.1.dist-info/METADATA
sophnet-0.0.1.dist-info/WHEEL
sophnet-0.0.1.dist-info/top_level.txt
sophnet-0.0.1.dist-info/RECORD
